mercury/robust/__init__.py
mercury/robust/_category_struct.py
mercury/robust/_label_cleaning.py
mercury/robust/_linalg.py
mercury/robust/_tree_analysis.py
mercury/robust/_treeselector.py
mercury/robust/basetests.py
mercury/robust/create_tutorials.py
mercury/robust/data_tests.py
mercury/robust/errors.py
mercury/robust/model_tests.py
mercury/robust/suite.py
mercury/robust/tutorials/RobustTestingExample.ipynb
mercury/robust/tutorials/TestSuite.ipynb
mercury/robust/tutorials/TestingModelsNLP.ipynb
mercury/robust/tutorials/data/bankintents/categories.json
mercury/robust/tutorials/data/bankintents/test.csv
mercury/robust/tutorials/data/bankintents/train.csv
mercury/robust/tutorials/data/credit/UCI_Credit_card.csv
mercury_robust-1.1.4.dist-info/LICENSE
mercury_robust-1.1.4.dist-info/METADATA
mercury_robust-1.1.4.dist-info/WHEEL
mercury_robust-1.1.4.dist-info/top_level.txt
mercury_robust-1.1.4.dist-info/RECORD
