Metadata-Version: 2.2
Name: mercury-robust
Version: 1.1.4
Summary: Mercury's robust is a library to perform robust testing on models and/or datasets..
Author-email: Mercury Team <mercury.group@bbva.com>
Project-URL: Homepage, https://github.com/BBVA/mercury-robust
Project-URL: Bug Tracker, https://github.com/BBVA/mercury-robust/issues
Classifier: Programming Language :: Python :: 3
Classifier: License :: OSI Approved :: Apache Software License
Classifier: Operating System :: OS Independent
Requires-Python: >=3.7
License-File: LICENSE
Requires-Dist: matplotlib>=3.0.2
Requires-Dist: pandas>=0.24.2
Requires-Dist: scikit-learn>=0.23.1
Requires-Dist: seaborn
Requires-Dist: mercury-dataschema
Requires-Dist: mercury-monitoring
Requires-Dist: psutil
Requires-Dist: cleanlab
Provides-Extra: dev
Requires-Dist: tensorflow<2.11; extra == "dev"
Requires-Dist: pytest; extra == "dev"
Requires-Dist: flake8; extra == "dev"
Requires-Dist: xgboost; extra == "dev"
Requires-Dist: mercury-explainability; extra == "dev"
Provides-Extra: doc
Requires-Dist: mkdocs; extra == "doc"
Requires-Dist: mkdocstrings[python]; extra == "doc"
Requires-Dist: mkdocs-material; extra == "doc"
Requires-Dist: mkdocs-minify-plugin==0.5.0; extra == "doc"
Requires-Dist: mkdocs-exclude; extra == "doc"
Requires-Dist: nbconvert; extra == "doc"
